<?xml version="1.0" encoding="UTF-8"?>
<configuration>

  <!-- 로그 파일 위치 및 이름 -->
  <property name="LOG_PATH" value="/app/logs"/>
  <property name="LOG_FILE_NAME" value="application.log"/>

  <!-- 로그 출력 포맷 (레벨별 색상 적용) -->
  <property name="LOG_PATTERN"
    value="%d{yyyy-MM-dd HH:mm:ss.SSS} [%thread] %highlight(%-5level) %logger{36} - %msg%n"/>

  <!-- 콘솔 로그 출력 -->
  <appender name="CONSOLE" class="ch.qos.logback.core.ConsoleAppender">
    <encoder>
      <pattern>${LOG_PATTERN}</pattern>
    </encoder>
  </appender>

  <!-- 파일 로그 출력 -->
  <appender name="FILE" class="ch.qos.logback.core.rolling.RollingFileAppender">
    <file>${LOG_PATH}/${LOG_FILE_NAME}</file>
    <rollingPolicy class="ch.qos.logback.core.rolling.TimeBasedRollingPolicy">
      <fileNamePattern>${LOG_PATH}/application.%d{yyyy-MM-dd}.log</fileNamePattern>
      <maxHistory>14</maxHistory>
    </rollingPolicy>
    <encoder>
      <pattern>${LOG_PATTERN}</pattern>
    </encoder>
  </appender>

  <!-- 전체 로그 레벨 설정 -->
  <root level="INFO">
    <appender-ref ref="CONSOLE"/>
    <appender-ref ref="FILE"/>
  </root>

</configuration>
